<?xml version="1.0" encoding="UTF-8"?>
<!DOCTYPE mapper PUBLIC "-//mybatis.org//DTD Mapper 3.0//EN" "http://mybatis.org/dtd/mybatis-3-mapper.dtd">
<mapper namespace="thanhtuu.springmvc.Dao.ExamsMapper">
	<resultMap id="BaseResultMap" type="thanhtuu.springmvc.Domain.Exams">
		<!-- WARNING - @mbggenerated This element is automatically generated by 
			MyBatis Generator, do not modify. This element was generated on Fri Feb 24 
			11:13:22 ICT 2017. -->
		<id column="id" jdbcType="INTEGER" property="id" />
		<result column="teacherId" jdbcType="INTEGER" property="teacherid" />
		<result column="subjectId" jdbcType="INTEGER" property="subjectid" />
		<result column="examCount" jdbcType="INTEGER" property="examcount" />
		<result column="questionCount" jdbcType="INTEGER" property="questioncount" />
		<result column="answerCount" jdbcType="INTEGER" property="answercount" />
		<result column="timeType" jdbcType="VARCHAR" property="timetype" />
		<result column="name" jdbcType="VARCHAR" property="name" />
		<result column="time" jdbcType="INTEGER" property="time" />
		<result column="times" jdbcType="INTEGER" property="times" />
		<result column="approverId" jdbcType="INTEGER" property="approverid" />
		<result column="status" jdbcType="VARCHAR" property="status" />
		<result column="startTime" jdbcType="DATE" property="starttime" />
		<result column="endTime" jdbcType="DATE" property="endtime" />
		<result column="modifiedAt" jdbcType="DATE" property="modifiedat" />
		<result column="createdAt" jdbcType="DATE" property="createdat" />
		<result column="examType" jdbcType="VARCHAR" property="examtype" />
	</resultMap>
	<sql id="Base_Column_List">
		<!-- WARNING - @mbggenerated This element is automatically generated by 
			MyBatis Generator, do not modify. This element was generated on Fri Feb 24 
			11:13:22 ICT 2017. -->
		id, teacherId, subjectId, examCount, questionCount, answerCount,
		timeType, name,
		time, times, approverId, status, startTime, endTime, modifiedAt, createdAt,
		examType
	</sql>
	<select id="selectByPrimaryKey" parameterType="Long" resultMap="BaseResultMap">
		<!-- WARNING - @mbggenerated This element is automatically generated by 
			MyBatis Generator, do not modify. This element was generated on Fri Feb 24 
			11:13:22 ICT 2017. -->
		select
		<include refid="Base_Column_List" />
		from exams
		where id = #{id,jdbcType=INTEGER}
	</select>
	<delete id="deleteByPrimaryKey" parameterType="Long">
		<!-- WARNING - @mbggenerated This element is automatically generated by 
			MyBatis Generator, do not modify. This element was generated on Fri Feb 24 
			11:13:22 ICT 2017. -->
		delete from exams
		where id = #{id,jdbcType=INTEGER}
	</delete>
	<insert id="insert" parameterType="thanhtuu.springmvc.Domain.Exams">
		<!-- WARNING - @mbggenerated This element is automatically generated by 
			MyBatis Generator, do not modify. This element was generated on Fri Feb 24 
			11:13:22 ICT 2017. -->
		insert into exams (id, teacherId, subjectId,
		examCount, questionCount, answerCount,
		timeType, name, time,
		times, approverId, status,
		startTime, endTime, modifiedAt,
		createdAt, examType)
		values (#{id,jdbcType=INTEGER}, #{teacherid,jdbcType=INTEGER},
		#{subjectid,jdbcType=INTEGER},
		#{examcount,jdbcType=INTEGER}, #{questioncount,jdbcType=INTEGER}, #{answercount,jdbcType=INTEGER},
		#{timetype,jdbcType=VARCHAR}, #{name,jdbcType=VARCHAR},
		#{time,jdbcType=INTEGER},
		#{times,jdbcType=INTEGER}, #{approverid,jdbcType=INTEGER}, #{status,jdbcType=VARCHAR},
		#{starttime,jdbcType=DATE}, #{endtime,jdbcType=DATE},
		#{modifiedat,jdbcType=DATE},
		#{createdat,jdbcType=DATE}, #{examtype,jdbcType=VARCHAR})
	</insert>
	<insert id="insertSelective" parameterType="thanhtuu.springmvc.Domain.Exams">
		<!-- WARNING - @mbggenerated This element is automatically generated by 
			MyBatis Generator, do not modify. This element was generated on Fri Feb 24 
			11:13:22 ICT 2017. -->
		insert into exams
		<trim prefix="(" suffix=")" suffixOverrides=",">
			<if test="id != null">
				id,
			</if>
			<if test="teacherid != null">
				teacherId,
			</if>
			<if test="subjectid != null">
				subjectId,
			</if>
			<if test="examcount != null">
				examCount,
			</if>
			<if test="questioncount != null">
				questionCount,
			</if>
			<if test="answercount != null">
				answerCount,
			</if>
			<if test="timetype != null">
				timeType,
			</if>
			<if test="name != null">
				name,
			</if>
			<if test="time != null">
				time,
			</if>
			<if test="times != null">
				times,
			</if>
			<if test="approverid != null">
				approverId,
			</if>
			<if test="status != null">
				status,
			</if>
			<if test="starttime != null">
				startTime,
			</if>
			<if test="endtime != null">
				endTime,
			</if>
			<if test="modifiedat != null">
				modifiedAt,
			</if>
			<if test="createdat != null">
				createdAt,
			</if>
			<if test="examtype != null">
				examType,
			</if>
		</trim>
		<trim prefix="values (" suffix=")" suffixOverrides=",">
			<if test="id != null">
				#{id,jdbcType=INTEGER},
			</if>
			<if test="teacherid != null">
				#{teacherid,jdbcType=INTEGER},
			</if>
			<if test="subjectid != null">
				#{subjectid,jdbcType=INTEGER},
			</if>
			<if test="examcount != null">
				#{examcount,jdbcType=INTEGER},
			</if>
			<if test="questioncount != null">
				#{questioncount,jdbcType=INTEGER},
			</if>
			<if test="answercount != null">
				#{answercount,jdbcType=INTEGER},
			</if>
			<if test="timetype != null">
				#{timetype,jdbcType=VARCHAR},
			</if>
			<if test="name != null">
				#{name,jdbcType=VARCHAR},
			</if>
			<if test="time != null">
				#{time,jdbcType=INTEGER},
			</if>
			<if test="times != null">
				#{times,jdbcType=INTEGER},
			</if>
			<if test="approverid != null">
				#{approverid,jdbcType=INTEGER},
			</if>
			<if test="status != null">
				#{status,jdbcType=VARCHAR},
			</if>
			<if test="starttime != null">
				#{starttime,jdbcType=DATE},
			</if>
			<if test="endtime != null">
				#{endtime,jdbcType=DATE},
			</if>
			<if test="modifiedat != null">
				#{modifiedat,jdbcType=DATE},
			</if>
			<if test="createdat != null">
				#{createdat,jdbcType=DATE},
			</if>
			<if test="examtype != null">
				#{examtype,jdbcType=VARCHAR},
			</if>
		</trim>
	</insert>
	<update id="updateByPrimaryKeySelective" parameterType="thanhtuu.springmvc.Domain.Exams">
		<!-- WARNING - @mbggenerated This element is automatically generated by 
			MyBatis Generator, do not modify. This element was generated on Fri Feb 24 
			11:13:22 ICT 2017. -->
		update exams
		<set>
			<if test="teacherid != null">
				teacherId = #{teacherid,jdbcType=INTEGER},
			</if>
			<if test="subjectid != null">
				subjectId = #{subjectid,jdbcType=INTEGER},
			</if>
			<if test="examcount != null">
				examCount = #{examcount,jdbcType=INTEGER},
			</if>
			<if test="questioncount != null">
				questionCount = #{questioncount,jdbcType=INTEGER},
			</if>
			<if test="answercount != null">
				answerCount = #{answercount,jdbcType=INTEGER},
			</if>
			<if test="timetype != null">
				timeType = #{timetype,jdbcType=VARCHAR},
			</if>
			<if test="name != null">
				name = #{name,jdbcType=VARCHAR},
			</if>
			<if test="time != null">
				time = #{time,jdbcType=INTEGER},
			</if>
			<if test="times != null">
				times = #{times,jdbcType=INTEGER},
			</if>
			<if test="approverid != null">
				approverId = #{approverid,jdbcType=INTEGER},
			</if>
			<if test="status != null">
				status = #{status,jdbcType=VARCHAR},
			</if>
			<if test="starttime != null">
				startTime = #{starttime,jdbcType=DATE},
			</if>
			<if test="endtime != null">
				endTime = #{endtime,jdbcType=DATE},
			</if>
			<if test="modifiedat != null">
				modifiedAt = #{modifiedat,jdbcType=DATE},
			</if>
			<if test="createdat != null">
				createdAt = #{createdat,jdbcType=DATE},
			</if>
			<if test="examtype != null">
				examType = #{examtype,jdbcType=VARCHAR},
			</if>
		</set>
		where id = #{id,jdbcType=INTEGER}
	</update>
	<update id="updateByPrimaryKey" parameterType="thanhtuu.springmvc.Domain.Exams">
		<!-- WARNING - @mbggenerated This element is automatically generated by 
			MyBatis Generator, do not modify. This element was generated on Fri Feb 24 
			11:13:22 ICT 2017. -->
		update exams
		set teacherId = #{teacherid,jdbcType=INTEGER},
		subjectId = #{subjectid,jdbcType=INTEGER},
		examCount = #{examcount,jdbcType=INTEGER},
		questionCount = #{questioncount,jdbcType=INTEGER},
		answerCount = #{answercount,jdbcType=INTEGER},
		timeType = #{timetype,jdbcType=VARCHAR},
		name = #{name,jdbcType=VARCHAR},
		time = #{time,jdbcType=INTEGER},
		times = #{times,jdbcType=INTEGER},
		approverId = #{approverid,jdbcType=INTEGER},
		status = #{status,jdbcType=VARCHAR},
		startTime = #{starttime,jdbcType=DATE},
		endTime = #{endtime,jdbcType=DATE},
		modifiedAt = #{modifiedat,jdbcType=DATE},
		createdAt = #{createdat,jdbcType=DATE},
		examType = #{examtype,jdbcType=VARCHAR}
		where id = #{id,jdbcType=INTEGER}
	</update>

	<select id="getByTeacherId" parameterType="Long" resultMap="BaseResultMap">
		select
		<include refid="Base_Column_List" />
		from exams
		where teacherId = #{teacherId,jdbcType=INTEGER}
	</select>

	<select id="getByStudentId" parameterType="Long" resultMap="BaseResultMap">
		select
		<include refid="Base_Column_List" />
		from exams
		where status like 'approved'
	</select>

	<select id="getBySubjectId" parameterType="Long" resultMap="BaseResultMap">
		select
		<include refid="Base_Column_List" />
		from exams
		where subjectId = #{subjectId,jdbcType=INTEGER}
	</select>

	<select id="getByIdInList" parameterType="list" resultMap="BaseResultMap">
		select
		<include refid="Base_Column_List" />
		from exams
		where id in
		<foreach close=")" collection="list" item="item" open="("
			separator=",">
			#{item}
		</foreach>
	</select>

	<select id="getByIdInListForStudent" parameterType="list"
		resultMap="BaseResultMap">
		select
		<include refid="Base_Column_List" />
		from exams
		where id in
		<foreach close=")" collection="list" item="item" open="("
			separator=",">
			#{item}
		</foreach>
		and status like 'approved'
	</select>

	<select id="getIDExamCurrent" resultMap="BaseResultMap">
		select
		<include refid="Base_Column_List" />
		from exams
		where id = (
		select max(id) from exams
		);

	</select>

	<select id="getRootExamId" parameterType="Long" resultMap="BaseResultMap">
		select
		<include refid="Base_Column_List" />
		from exams
		where id =#{id,jdbcType=INTEGER};
	</select>

	<select id="getAllSubjectOfTeacher" parameterType="Long"
		resultMap="BaseResultMap">
		select
		<include refid="Base_Column_List" />
		from exams
		where teacherId = #{teacherId,jdbcType=INTEGER} and
		examType = #{examType,jdbcType=VARCHAR}
		group by subjectId
	</select>



	<select id="getAllExamOfSubjectOfTeacher" parameterType="Long"
		resultMap="BaseResultMap">
		select
		<include refid="Base_Column_List" />
		from exams
		where teacherId = #{teacherId,jdbcType=INTEGER} and
		examType = #{examType,jdbcType=VARCHAR} and
		subjectId = #{subjectId,jdbcType=INTEGER}

	</select>

	<select id="selectByID" parameterType="Long" resultMap="BaseResultMap">
		select
		<include refid="Base_Column_List" />
		from exams
		where
		id = #{id,jdbcType=INTEGER}
	</select>

</mapper>